kunna/__init__.py
kunna/cli.py
kunna/data/Q1.md
kunna/data/Q10.md
kunna/data/Q11.md
kunna/data/Q12.md
kunna/data/Q13.md
kunna/data/Q14.md
kunna/data/Q15.md
kunna/data/Q2.md
kunna/data/Q3.md
kunna/data/Q4.md
kunna/data/Q5.md
kunna/data/Q6.md
kunna/data/Q7.md
kunna/data/Q8.md
kunna/data/Q9.md
kunna-0.1.0.dist-info/licenses/LICENSE
kunna-0.1.0.dist-info/METADATA
kunna-0.1.0.dist-info/WHEEL
kunna-0.1.0.dist-info/entry_points.txt
kunna-0.1.0.dist-info/top_level.txt
kunna-0.1.0.dist-info/RECORD
