Metadata-Version: 2.4
Name: kunna
Version: 0.1.0
Summary: A CLI tool to display Q&A content
Author: Basil Shaji
License: MIT
Classifier: Programming Language :: Python :: 3
Classifier: License :: OSI Approved :: MIT License
Classifier: Operating System :: OS Independent
Requires-Python: >=3.6
License-File: LICENSE
Dynamic: license-file
Dynamic: requires-python
